jetz/__init__.py
jetz/base.py
jetz/err.py
jetz/tarf.py
jetz/zipf.py
jetar_zip-0.0.4.dist-info/METADATA
jetar_zip-0.0.4.dist-info/WHEEL
jetar_zip-0.0.4.dist-info/top_level.txt
jetar_zip-0.0.4.dist-info/RECORD
