Metadata-Version: 2.1
Name: jetar-zip
Version: 0.0.4
Summary: A zip/tar file saver for cache
Home-page: UNKNOWN
Author: jeef
Author-email: jeefyol@outlook.com
Maintainer: Jeefy
Maintainer-email: jeefy163@163.com
License: UNKNOWN
Platform: UNKNOWN
